topsis_jayati/topsis.py
TOPSIS_Jayati_101803546-1.0.0.dist-info/LICENSE
TOPSIS_Jayati_101803546-1.0.0.dist-info/METADATA
TOPSIS_Jayati_101803546-1.0.0.dist-info/WHEEL
TOPSIS_Jayati_101803546-1.0.0.dist-info/entry_points.txt
TOPSIS_Jayati_101803546-1.0.0.dist-info/top_level.txt
TOPSIS_Jayati_101803546-1.0.0.dist-info/RECORD
