Metadata-Version: 2.1
Name: TOPSIS-Jayati-101803546
Version: 1.0.0
Summary: A Python package implementing TOPSIS technique.
Home-page: https://github.com/JayatiGumber/topsis-jayati-101803546
Author: Jayati Gumber
Author-email: jayatigumber@gmail.com
License: MIT
Platform: UNKNOWN
Classifier: License :: OSI Approved :: MIT License
Classifier: Programming Language :: Python :: 3
Classifier: Programming Language :: Python :: 3.7
Requires-Dist: scipy
Requires-Dist: tabulate
Requires-Dist: numpy
Requires-Dist: pandas
